rst2textile.py
docutils_textile/builder.py
docutils_textile/main.py
docutils_textile/writer.py
docutils_textile/__init__.py
rst2textile-0.2.1.data/scripts/rst2textile.py
rst2textile-0.2.1.dist-info/DESCRIPTION.rst
rst2textile-0.2.1.dist-info/METADATA
rst2textile-0.2.1.dist-info/metadata.json
rst2textile-0.2.1.dist-info/RECORD
rst2textile-0.2.1.dist-info/top_level.txt
rst2textile-0.2.1.dist-info/WHEEL
