Metadata-Version: 2.0
Name: rst2textile
Version: 0.2.1
Summary: rst2textile is docutils textile writer convert reStructuredText(rst) to Textile format.
Home-page: https://bitbucket.org/shimizukawa/rst2textile
Author: Takayuki SHIMIZUKAWA
Author-email: shimizukawa@gmail.com
License: UNKNOWN
Keywords: docutils reStructuredText textile
Platform: UNKNOWN
Classifier: Development Status :: 3 - Alpha
Classifier: Topic :: Utilities
Classifier: Environment :: Other Environment
Classifier: License :: OSI Approved :: Apache Software License
Classifier: Topic :: Documentation
Classifier: Topic :: Text Processing :: General
Classifier: Programming Language :: Python :: 2
Classifier: Programming Language :: Python :: 2.6
Classifier: Programming Language :: Python :: 2.7
Classifier: Programming Language :: Python :: 3
Classifier: Programming Language :: Python :: 3.3
Classifier: Programming Language :: Python :: 3.4
Requires-Dist: docutils
Provides-Extra: test
Requires-Dist: tox; extra == 'test'
